README.txt
setup.cfg
setup.py
collective/__init__.py
collective.atimage.transformmenu.egg-info/PKG-INFO
collective.atimage.transformmenu.egg-info/SOURCES.txt
collective.atimage.transformmenu.egg-info/dependency_links.txt
collective.atimage.transformmenu.egg-info/entry_points.txt
collective.atimage.transformmenu.egg-info/namespace_packages.txt
collective.atimage.transformmenu.egg-info/not-zip-safe
collective.atimage.transformmenu.egg-info/requires.txt
collective.atimage.transformmenu.egg-info/top_level.txt
collective/atimage/__init__.py
collective/atimage/transformmenu/README.txt
collective/atimage/transformmenu/__init__.py
collective/atimage/transformmenu/configure.zcml
collective/atimage/transformmenu/interfaces.py
collective/atimage/transformmenu/version.txt
collective/atimage/transformmenu/Extensions/Install.py
collective/atimage/transformmenu/browser/__init__.py
collective/atimage/transformmenu/browser/configure.zcml
collective/atimage/transformmenu/browser/interfaces.py
collective/atimage/transformmenu/browser/menu.py
collective/atimage/transformmenu/browser/transform.py
collective/atimage/transformmenu/browser/resources/transformmenu.js
collective/atimage/transformmenu/profiles/default/browserlayer.xml
collective/atimage/transformmenu/profiles/default/jsregistry.xml
collective/atimage/transformmenu/profiles/default/types/Image.xml
collective/atimage/transformmenu/profiles/uninstall/types/Image.xml
collective/atimage/transformmenu/tests/__init__.py
collective/atimage/transformmenu/tests/base.py
collective/atimage/transformmenu/tests/test_doctest.py
collective/atimage/transformmenu/tests/samples/test_image.png
docs/AUTHORS.txt
docs/HISTORY.txt
docs/INSTALL.txt
docs/LICENSE.GPL
docs/LICENSE.txt