Metadata-Version: 1.0
Name: collective.atimage.transformmenu
Version: 1.2
Summary: Replaces Transforms tab with a menu
Home-page: http://svn.plone.org/svn/collective/collective.atimage.transformmenu
Author: marcosfromero
Author-email: marcos.romero {at} inter-cultura {dot} com
License: GPL
Platform: UNKNOWN
Classifier: Framework :: Plone
Classifier: Programming Language :: Python
